URBasic/__init__.py
URBasic/advanced_data_analyzer.py
URBasic/advanced_data_recorder.py
URBasic/advanced_multi_robot_coordinator.py
URBasic/advanced_trajectory_planner.py
URBasic/auto_recovery.py
URBasic/connectionState.py
URBasic/dashboard.py
URBasic/error_handling.py
URBasic/force_control.py
URBasic/manipulation.py
URBasic/multi_robot_coordinator.py
URBasic/operation_history.py
URBasic/realTimeClient.py
URBasic/register_reset_test.py
URBasic/robotConnector.py
URBasic/robotModel.py
URBasic/rtde.py
URBasic/rtdeConfigurationDefault.xml
URBasic/status_monitor.py
URBasic/task_queue.py
URBasic/trajectory_planner.py
URBasic/urScript.py
URBasic/urScriptExt.py
URBasic/user_friendly_errors.py
nonead_universal_robots_mcp/nonead_universal_robots_mcp/__init__.py
nonead_universal_robots_mcp/nonead_universal_robots_mcp/server.py
nonead_universal_robots_mcp-0.1.1.dist-info/licenses/LICENSE
nonead_universal_robots_mcp-0.1.1.dist-info/METADATA
nonead_universal_robots_mcp-0.1.1.dist-info/WHEEL
nonead_universal_robots_mcp-0.1.1.dist-info/entry_points.txt
nonead_universal_robots_mcp-0.1.1.dist-info/top_level.txt
nonead_universal_robots_mcp-0.1.1.dist-info/RECORD
