Metadata-Version: 2.4
Name: nonead-universal-robots-mcp
Version: 0.1.1
Summary: Nonead Universal Robots MCP
Classifier: Programming Language :: Python :: 3
Classifier: License :: OSI Approved :: MIT License
Classifier: Operating System :: OS Independent
Requires-Python: <3.13,>=3.12
License-File: LICENSE
Requires-Dist: bitstring==4.3.1
Requires-Dist: ikpy==3.4.2
Requires-Dist: lxml==5.4.0
Requires-Dist: matplotlib==3.10.1
Requires-Dist: mcp[cli]==1.6.0
Requires-Dist: numpy==2.1.3
Requires-Dist: pandas==2.2.3
Requires-Dist: pydantic==2.11.3
Requires-Dist: pymodbus==3.9.2
Requires-Dist: pyserial==3.5
Requires-Dist: scipy==1.15.2
Requires-Dist: six==1.17.0
Requires-Dist: sympy==1.14.0
Requires-Dist: tensorflow==2.19.0
Requires-Dist: paramiko==3.5.1
Requires-Dist: seaborn==0.13.2
Requires-Dist: scikit-learn==1.8.0
Dynamic: license-file
